{
  "configVersion": 1,
  "index": "/index.html",
  "assetGroups": [
    {
      "name": "app",
      "installMode": "prefetch",
      "updateMode": "prefetch",
      "urls": [
        "/favicon.ico",
        "/index.html",
        "/main.f05cd945661f3cdea2ce.js",
        "/polyfills.a3af1614dc3712538dd6.js",
        "/runtime.a5dd35324ddfd942bef1.js",
        "/styles.12d3eb4eef0622fff548.css"
      ],
      "patterns": []
    },
    {
      "name": "assets",
      "installMode": "lazy",
      "updateMode": "prefetch",
      "urls": [
        "/assets/icons/icon-144x144.png"
      ],
      "patterns": []
    }
  ],
  "dataGroups": [],
  "hashTable": {
    "/assets/icons/icon-144x144.png": "ae2a0cd9572c14ef94c96900b34bceb620a7c00c",
    "/favicon.ico": "34b41b827be8ec450ce9bca120f683b91eedfed9",
    "/index.html": "4c5c56973d72dd6809945829320737529ef7fdf2",
    "/main.f05cd945661f3cdea2ce.js": "719c392a1630676cd5c5c1d25745831ede5d073a",
    "/polyfills.a3af1614dc3712538dd6.js": "6946e10a03311677a01490b8e91741668e64e17e",
    "/runtime.a5dd35324ddfd942bef1.js": "b62956c2192bfe5516d6374e753773901ed50ec5",
    "/styles.12d3eb4eef0622fff548.css": "3a273fe86376fe8738a3fa4213c3f7468247563b"
  },
  "navigationUrls": [
    {
      "positive": true,
      "regex": "^\\/.*$"
    },
    {
      "positive": false,
      "regex": "^\\/(?:.+\\/)?[^/]*\\.[^/]*$"
    },
    {
      "positive": false,
      "regex": "^\\/(?:.+\\/)?[^/]*__[^/]*$"
    },
    {
      "positive": false,
      "regex": "^\\/(?:.+\\/)?[^/]*__[^/]*\\/.*$"
    }
  ]
}